autopocket/__init__.py
autopocket/main.py
autopocket/algorithms/Modeller.py
autopocket/algorithms/__init__.py
autopocket/algorithms/base.py
autopocket/algorithms/classification.py
autopocket/algorithms/regression.py
autopocket/algorithms/utils.py
autopocket/postprocessing/ICEPlotter.py
autopocket/postprocessing/LimePostProcessor.py
autopocket/postprocessing/ModelsLeaderboard.py
autopocket/postprocessing/PartialDependencePlotter.py
autopocket/postprocessing/Postprocessor.py
autopocket/postprocessing/__init__.py
autopocket/postprocessing/shap.py
autopocket/postprocessing/utils.py
autopocket/preprocessing/Preprocessor.py
autopocket/preprocessing/__init__.py
autopocket/preprocessing/data_cleaning/DataCleaner.py
autopocket/preprocessing/data_cleaning/__init__.py
autopocket/preprocessing/data_cleaning/cleaner_tools/BinaryColumnHandler.py
autopocket/preprocessing/data_cleaning/cleaner_tools/DataImputer.py
autopocket/preprocessing/data_cleaning/cleaner_tools/DateHandler.py
autopocket/preprocessing/data_cleaning/cleaner_tools/NumberFormatFixer.py
autopocket/preprocessing/data_cleaning/cleaner_tools/PatternRemover.py
autopocket/preprocessing/data_cleaning/cleaner_tools/RedundantColumnRemover.py
autopocket/preprocessing/data_cleaning/cleaner_tools/StringStripper.py
autopocket/preprocessing/data_cleaning/cleaner_tools/StringToLowerConverter.py
autopocket/preprocessing/data_cleaning/cleaner_tools/__init__.py
autopocket/preprocessing/feature_processing/FeatureProcessor.py
autopocket/preprocessing/feature_processing/__init__.py
autopocket/preprocessing/feature_processing/processing_tools/FeatureEncoder.py
autopocket/preprocessing/feature_processing/processing_tools/FeatureSelector.py
autopocket/preprocessing/feature_processing/processing_tools/OutlierHandler.py
autopocket/preprocessing/feature_processing/processing_tools/__init__.py
autopocket/preprocessing/task_analysing/ColumnTypeAnalyzer.py
autopocket/preprocessing/task_analysing/__init__.py
autopocket-0.11.0.dist-info/LICENSE.txt
autopocket-0.11.0.dist-info/METADATA
autopocket-0.11.0.dist-info/WHEEL
autopocket-0.11.0.dist-info/top_level.txt
autopocket-0.11.0.dist-info/RECORD
